{
    "display": {
        "icon": {
            "item": "minecraft:enchanted_golden_apple"
        },
        "title": "Up a Notch",
        "description": "Iss einen Notch Apfel (enchanted golden apple).",
        "frame": "goal",
        "show_toast": true,
        "announce_to_chat": true,
        "hidden": true
    },
    "parent": "minecraft:husbandry/golden",
    "criteria": {
        "requirement": {
            "trigger": "minecraft:consume_item",
            "conditions": {
                "item": {
                    "items": ["minecraft:enchanted_golden_apple"]
                }
            }
        }
    }
}
